parsec/__init__.py
parsec/__main__.py
parsec/_parsec.cp312-win_amd64.pyd
parsec/_parsec.pyi
parsec/_parsec_pyi/__init__.pyi
parsec/_parsec_pyi/addrs.pyi
parsec/_parsec_pyi/certif.pyi
parsec/_parsec_pyi/crypto.pyi
parsec/_parsec_pyi/enumerate.pyi
parsec/_parsec_pyi/ids.pyi
parsec/_parsec_pyi/manifest.pyi
parsec/_parsec_pyi/misc.pyi
parsec/_parsec_pyi/pki.pyi
parsec/_parsec_pyi/protocol/__init__.pyi
parsec/_parsec_pyi/protocol/anonymous_cmds/__init__.pyi
parsec/_parsec_pyi/protocol/anonymous_cmds/v5/__init__.pyi
parsec/_parsec_pyi/protocol/anonymous_cmds/v5/organization_bootstrap.pyi
parsec/_parsec_pyi/protocol/anonymous_cmds/v5/ping.pyi
parsec/_parsec_pyi/protocol/anonymous_cmds/v5/pki_enrollment_info.pyi
parsec/_parsec_pyi/protocol/anonymous_cmds/v5/pki_enrollment_submit.pyi
parsec/_parsec_pyi/protocol/anonymous_server_cmds/__init__.pyi
parsec/_parsec_pyi/protocol/anonymous_server_cmds/v5/__init__.pyi
parsec/_parsec_pyi/protocol/anonymous_server_cmds/v5/account_create_proceed.pyi
parsec/_parsec_pyi/protocol/anonymous_server_cmds/v5/account_create_send_validation_email.pyi
parsec/_parsec_pyi/protocol/anonymous_server_cmds/v5/account_recover_proceed.pyi
parsec/_parsec_pyi/protocol/anonymous_server_cmds/v5/account_recover_send_validation_email.pyi
parsec/_parsec_pyi/protocol/anonymous_server_cmds/v5/auth_method_password_get_algorithm.pyi
parsec/_parsec_pyi/protocol/anonymous_server_cmds/v5/ping.pyi
parsec/_parsec_pyi/protocol/anonymous_server_cmds/v5/server_config.pyi
parsec/_parsec_pyi/protocol/authenticated_account_cmds/__init__.pyi
parsec/_parsec_pyi/protocol/authenticated_account_cmds/v5/__init__.pyi
parsec/_parsec_pyi/protocol/authenticated_account_cmds/v5/account_delete_proceed.pyi
parsec/_parsec_pyi/protocol/authenticated_account_cmds/v5/account_delete_send_validation_email.pyi
parsec/_parsec_pyi/protocol/authenticated_account_cmds/v5/account_info.pyi
parsec/_parsec_pyi/protocol/authenticated_account_cmds/v5/auth_method_create.pyi
parsec_cloud-3.7.1.dist-info/entry_points.txt
parsec_cloud-3.7.1.dist-info/METADATA
parsec_cloud-3.7.1.dist-info/WHEEL
parsec_cloud-3.7.1.dist-info/RECORD
